README.md
setup.py
LPPPy.egg-info/PKG-INFO
LPPPy.egg-info/SOURCES.txt
LPPPy.egg-info/dependency_links.txt
LPPPy.egg-info/entry_points.txt
LPPPy.egg-info/requires.txt
LPPPy.egg-info/top_level.txt
lpppy/__init__.py
lpppy/__main__.py
lpppy/main.py
lpppy/compiler/__init__.py
lpppy/compiler/code.py
lpppy/compiler/error.py
lpppy/compiler/lex.py
lpppy/compiler/main.py
lpppy/compiler/parse.py
lpppy/compiler/symtab.py
lpppy/compiler/token.py