Metadata-Version: 2.1
Name: LPPPy
Version: 0.1.0
Summary: A compiler to Python of Manzano's LPP
Home-page: https://github.com/leozamboni/LPPPy
Author: Zamboni Leonardo
Author-email: leonardonunes169@gmail.com
License: MIT
Platform: UNKNOWN
Classifier: License :: OSI Approved :: MIT License
Classifier: Programming Language :: Python :: 3
Classifier: Programming Language :: Python :: 3.7
Classifier: Programming Language :: Python :: 3.8
Classifier: Programming Language :: Python :: 3.9
Classifier: Programming Language :: Python :: 3.10
